Source_Files/alu.v
module alu (
    input [31:0] a, b,
    input [3:0] alu_ctrl,
    output reg [31:0] result,
    output zero
);

    always @(*) begin
        case (alu_ctrl)
            4'b0000: result = a & b; // And
            4'b0001: result = a | b; // OR
            4'b0010: result = a + b; // ADD
            4'b0110: result = a - b; // SUB
            4'b0111: result = ($signed(a) < $signed(b)) ? 1 : 0; // SLT (signed comparison)
            4'b1000: result = a ^ b; // XOR
            4'b1001: result = a >> b[4:0]; // SRL (shift right logical)
            4'b1010: result = $signed(a) >>> b[4:0]; // SRA (shift right arithmetic)
            4'b1011: result = a << b[4:0]; // SLL (shift left logical)
            4'b1100: result = (a < b) ? 1 : 0; // SLTU (set less than unsigned)
            4'b1101: result = b; // LUI: pass B (upper immediate)
            default: result = 0; // Default case to handle undefined control signals
        endcase
    end

    assign zero = (result == 0); // Zero flag is set if the result is zero

endmodule

TestBenches/tb_alu.v
`timescale 1ns / 1ps

module alu_tb();

    // Inputs
    reg [31:0] a;
    reg [31:0] b;
    reg [3:0] alu_ctrl;

    // Outputs
    wire [31:0] result;
    wire zero;

    // Instantiate the Unit Under Test (UUT)
    alu uut (
        .a(a), 
        .b(b), 
        .alu_ctrl(alu_ctrl), 
        .result(result), 
        .zero(zero)
    );

    initial begin
        // Initialize Inputs
        a = 0; b = 0; alu_ctrl = 0;

        // Wait 10 ns
        #10;
        
        $display("Starting ALU Test...");
        $monitor("Time=%0t | Ctrl=%b | A=%h | B=%h | Res=%h | Zero=%b", $time, alu_ctrl, a, b, result, zero);

        // Test Case 1: ADD
        // Expected Result: 30, Zero = 0
        a = 32'd10; b = 32'd20; alu_ctrl = 4'b0010; 
        #10;
        
        // Test Case 2: SUB (Result Zero)
        // Expected Result: 0, Zero = 1
        a = 32'd50; b = 32'd50; alu_ctrl = 4'b0110; 
        #10;

        // Test Case 3: AND
        // Expected Result: 0x5555_0000, Zero = 0
        a = 32'hAAAA_AAAA; b = 32'h5555_FFFF; alu_ctrl = 4'b0000; 
        #10;

        // Test Case 4: OR
        // Expected Result: 0xF0F0_F0F0, Zero = 0
        a = 32'hF0F0_F0F0; b = 32'h0F0F_0F0F; alu_ctrl = 4'b0001; 
        #10;

        // Test Case 5: SLT (Signed Less Than) - Negative check 
        // Expected Result: 1, Zero = 0
        a = 32'hFFFF_FFFF; // -1 in two's complement
        b = 32'h0000_0001; // +1
        alu_ctrl = 4'b0111; 
        #10;

        // Test Case 6: SLL (Shift Left Logical)
        // Expected Result: 0x0000_0010, Zero = 0
        a = 32'h0000_0001; b = 32'd4; alu_ctrl = 4'b1011; 
        #10;

        // Test Case 7: SRA (Shift Right Arithmetic) - Sign extension
        // Expected Result: 0xFFFF_FFFF, Zero = 0
        a = 32'h8000_0000; b = 32'd2; alu_ctrl = 4'b1010; 
        #10;

        // Test Case 8: XOR
        // Expected Result: 0xFFFF_FFFF, Zero = 0
        a = 32'h1234_5678; b = 32'h1234_5678; alu_ctrl = 4'b1000; 
        #10;

        $display("ALU Test Completed.");
        $finish;
    end

    initial begin
        $dumpfile("alu_op.vcd");
        $dumpvars(0, alu_tb);
    end
      
endmodule

/* 
VCD OUTPUT: 
Starting ALU Test...
Time=10000 | Ctrl=0010 | A=0000000a | B=00000014 | Res=0000001e | Zero=0
Time=20000 | Ctrl=0110 | A=00000032 | B=00000032 | Res=00000000 | Zero=1
Time=30000 | Ctrl=0000 | A=aaaaaaaa | B=5555ffff | Res=0000aaaa | Zero=0
Time=40000 | Ctrl=0001 | A=f0f0f0f0 | B=0f0f0f0f | Res=ffffffff | Zero=0
Time=50000 | Ctrl=0111 | A=ffffffff | B=00000001 | Res=00000001 | Zero=0
Time=60000 | Ctrl=1011 | A=00000001 | B=00000004 | Res=00000010 | Zero=0
Time=70000 | Ctrl=1010 | A=80000000 | B=00000002 | Res=e0000000 | Zero=0
Time=80000 | Ctrl=1000 | A=12345678 | B=12345678 | Res=00000000 | Zero=1
ALU Test Completed.
*/

VCDFiles/alu_op.vcd
$date
	Sat Apr 25 03:06:01 2026
$end
$version
	Icarus Verilog
$end
$timescale
	1ps
$end
$scope module alu_tb $end
$var wire 1 ! zero $end
$var wire 32 " result [31:0] $end
$var reg 32 # a [31:0] $end
$var reg 4 $ alu_ctrl [3:0] $end
$var reg 32 % b [31:0] $end
$scope module uut $end
$var wire 32 & a [31:0] $end
$var wire 4 ' alu_ctrl [3:0] $end
$var wire 32 ( b [31:0] $end
$var wire 1 ! zero $end
$var reg 32 ) result [31:0] $end
$upscope $end
$upscope $end
$enddefinitions $end
$comment Show the parameter values. $end
$dumpall
$end
#0
$dumpvars
b0 )
b0 (
b0 '
b0 &
b0 %
b0 $
b0 #
b0 "
1!
$end
#10000
0!
b11110 "
b11110 )
b10 $
b10 '
b10100 %
b10100 (
b1010 #
b1010 &
#20000
1!
b0 "
b0 )
b110 $
b110 '
b110010 %
b110010 (
b110010 #
b110010 &
#30000
0!
b1010101010101010 "
b1010101010101010 )
b0 $
b0 '
b1010101010101011111111111111111 %
b1010101010101011111111111111111 (
b10101010101010101010101010101010 #
b10101010101010101010101010101010 &
#40000
b11111111111111111111111111111111 "
b11111111111111111111111111111111 )
b1 $
b1 '
b1111000011110000111100001111 %
b1111000011110000111100001111 (
b11110000111100001111000011110000 #
b11110000111100001111000011110000 &
#50000
b1 "
b1 )
b111 $
b111 '
b1 %
b1 (
b11111111111111111111111111111111 #
b11111111111111111111111111111111 &
#60000
b10000 "
b10000 )
b1011 $
b1011 '
b100 %
b100 (
b1 #
b1 &
#70000
b11100000000000000000000000000000 "
b11100000000000000000000000000000 )
b1010 $
b1010 '
b10 %
b10 (
b10000000000000000000000000000000 #
b10000000000000000000000000000000 &
#80000
1!
b0 "
b0 )
b1000 $
b1000 '
b10010001101000101011001111000 %
b10010001101000101011001111000 (
b10010001101000101011001111000 #
b10010001101000101011001111000 &
