Source_Files/alu_control.v
module alu_control (
    input [1:0] alu_op, // defines the type of instruction 
    input [2:0] funct3, // defines the specific operation for R-type and I-type instructions
    input [6:0] funct7, // differentiates between certain R-type instructions (ADD vs SUB)
    output reg [3:0] alu_ctrl // final control signal for the ALU 
);

    always @(*) begin
        case (alu_op)
            2'b00: alu_ctrl = 4'b0010; // Load/Store: ADD
            2'b01: alu_ctrl = 4'b0110; // Branch: SUB (for BEQ/BNE), BLT/BGE handled in branch_control
            2'b11: alu_ctrl = 4'b1101; // LUI: pass B
            2'b10: case (funct3) // R-type / I-type
                3'b000: alu_ctrl = (funct7[5]) ? 4'b0110 : 4'b0010; // SUB/ADD
                3'b001: alu_ctrl = 4'b1011; // SLL
                3'b010: alu_ctrl = 4'b0111; // SLT
                3'b011: alu_ctrl = 4'b1100; // SLTU
                3'b100: alu_ctrl = 4'b1000; // XOR
                3'b101: alu_ctrl = (funct7[5]) ? 4'b1010 : 4'b1001; // SRA/SRL
                3'b110: alu_ctrl = 4'b0001; // OR
                3'b111: alu_ctrl = 4'b0000; // AND
                default: alu_ctrl = 4'b0010; // Default to ADD for unknown funct3
            endcase
            default: alu_ctrl = 4'b0010; // Default to ADD for unknown alu_op
        endcase
    end

endmodule

TestBenches/tb_alu_control.v
`timescale 1ns / 1ps

module alu_control_tb();

    // Inputs
    reg [1:0] alu_op;
    reg [2:0] funct3;
    reg [6:0] funct7;

    // Output
    wire [3:0] alu_ctrl;

    // Instantiate the Unit Under Test (UUT)
    alu_control uut (
        .alu_op(alu_op), 
        .funct3(funct3), 
        .funct7(funct7), 
        .alu_ctrl(alu_ctrl)
    );

    initial begin
        // Initialize Inputs
        alu_op = 0; funct3 = 0; funct7 = 0;

        $display("Starting ALU Control Test...");
        $monitor("Time=%0t | ALUOp=%b | F3=%b | F7[5]=%b | Result Ctrl=%b", $time, alu_op, funct3, funct7[5], alu_ctrl);

        // Test 1: Load/Store (alu_op = 00)
        // Expected: ADD (0010)
        alu_op = 2'b00; #10;

        // Test 2: Branch (alu_op = 01)
        // Expected: SUB (0110)
        alu_op = 2'b01; #10;

        // Test 3: LUI (alu_op = 11)
        // Expected: Pass B (1101)
        alu_op = 2'b11; #10;

        // Test 4: R-type/I-type (alu_op = 10)
        alu_op = 2'b10;

        // Sub-test: ADD (funct3 = 000, funct7[5] = 0)
        // Expected: ADD (0010)
        funct3 = 3'b000; funct7 = 7'b0000000; #10;

        // Sub-test: SUB (funct3 = 000, funct7[5] = 1)
        // Expected: SUB (0110)
        funct3 = 3'b000; funct7 = 7'b0100000; #10;

        // Sub-test: SLL (funct3 = 001)
        // Expected: SLL (0001)
        funct3 = 3'b001; #10;

        // Sub-test: SLT (funct3 = 010)
        // Expected: SLT (0111)
        funct3 = 3'b010; #10;

        // Sub-test: XOR (funct3 = 100)
        // Expected: XOR (0011)
        funct3 = 3'b100; #10;

        // Sub-test: SRL (funct3 = 101, funct7[5] = 0)
        // Expected: SRL (0101)
        funct3 = 3'b101; funct7 = 7'b0000000; #10;

        // Sub-test: SRA (funct3 = 101, funct7[5] = 1)
        // Expected: SRA (1100)
        funct3 = 3'b101; funct7 = 7'b0100000; #10;

        // Sub-test: OR (funct3 = 110)
        // Expected: OR (0000)
        funct3 = 3'b110; #10;

        // Sub-test: AND (funct3 = 111)
        // Expected: AND (0001)
        funct3 = 3'b111; #10;

        $display("ALU Control Test Completed.");
        $finish;
    end

    initial begin
        $dumpfile("alu_control_op.vcd");
        $dumpvars(0, alu_control_tb);
    end
      
endmodule

/* 
VCD OUTPUT:
Time=0 | ALUOp=00 | F3=000 | F7[5]=0 | Result Ctrl=0010
Time=10000 | ALUOp=01 | F3=000 | F7[5]=0 | Result Ctrl=0110
Time=20000 | ALUOp=11 | F3=000 | F7[5]=0 | Result Ctrl=1101
Time=30000 | ALUOp=10 | F3=000 | F7[5]=0 | Result Ctrl=0010
Time=40000 | ALUOp=10 | F3=000 | F7[5]=1 | Result Ctrl=0110
Time=50000 | ALUOp=10 | F3=001 | F7[5]=1 | Result Ctrl=1011
Time=60000 | ALUOp=10 | F3=010 | F7[5]=1 | Result Ctrl=0111
Time=70000 | ALUOp=10 | F3=100 | F7[5]=1 | Result Ctrl=1000
Time=80000 | ALUOp=10 | F3=101 | F7[5]=0 | Result Ctrl=1001
Time=90000 | ALUOp=10 | F3=101 | F7[5]=1 | Result Ctrl=1010
Time=100000 | ALUOp=10 | F3=110 | F7[5]=1 | Result Ctrl=0001
Time=110000 | ALUOp=10 | F3=111 | F7[5]=1 | Result Ctrl=0000
ALU Control Test Completed.
*/

VCDFiles/alu_control_op.vcd
$date
	Sat Apr 25 02:56:32 2026
$end
$version
	Icarus Verilog
$end
$timescale
	1ps
$end
$scope module alu_control_tb $end
$var wire 4 ! alu_ctrl [3:0] $end
$var reg 2 " alu_op [1:0] $end
$var reg 3 # funct3 [2:0] $end
$var reg 7 $ funct7 [6:0] $end
$scope module uut $end
$var wire 2 % alu_op [1:0] $end
$var wire 3 & funct3 [2:0] $end
$var wire 7 ' funct7 [6:0] $end
$var reg 4 ( alu_ctrl [3:0] $end
$upscope $end
$upscope $end
$enddefinitions $end
$comment Show the parameter values. $end
$dumpall
$end
#0
$dumpvars
b10 (
b0 '
b0 &
b0 %
b0 $
b0 #
b0 "
b10 !
$end
#10000
b110 !
b110 (
b1 "
b1 %
#20000
b1101 !
b1101 (
b11 "
b11 %
#30000
b10 !
b10 (
b10 "
b10 %
#40000
b110 !
b110 (
b100000 $
b100000 '
#50000
b1011 !
b1011 (
b1 #
b1 &
#60000
b111 !
b111 (
b10 #
b10 &
#70000
b1000 !
b1000 (
b100 #
b100 &
#80000
b1001 !
b1001 (
b0 $
b0 '
b101 #
b101 &
#90000
b1010 !
b1010 (
b100000 $
b100000 '
#100000
b1 !
b1 (
b110 #
b110 &
#110000
b0 !
b0 (
b111 #
b111 &
