Source_Files/branch_control.v
// decides if a branch should be taken based on the branch type and ALU results
// brach means to jump to a different instruction address if a certain condition is met 
module branch_control (
    input branch,
    input zero,
    input [31:0] alu_result,
    input [2:0] funct3,
    output reg pc_branch
);

    always @(*) begin
        pc_branch = 1'b0;
        if (branch) begin
            case (funct3)
                3'b000: pc_branch = zero; // BEQ (branch if equal)
                3'b001: pc_branch = ~zero; // BNE (branch if not equal)
                3'b100: pc_branch = alu_result[0]; // BLT  (branch if less than, signed)
                3'b101: pc_branch = ~alu_result[0]; // BGE  (branch if greater than or equal, signed)
                3'b110: pc_branch = alu_result[0]; // BLTU (branch if less than, unsigned)
                3'b111: pc_branch = ~alu_result[0]; // BGEU (branch if greater than or equal, unsigned)
                default: pc_branch = 1'b0;
            endcase
        end
    end

endmodule

TestBenches/tb_branch_control.v
`timescale 1ns / 1ps

module branch_control_tb();

    // Inputs
    reg branch;
    reg zero;
    reg [31:0] alu_result;
    reg [2:0] funct3;

    // Output
    wire pc_branch;

    // Instantiate UUT
    branch_control uut (
        .branch(branch),
        .zero(zero),
        .alu_result(alu_result),
        .funct3(funct3),
        .pc_branch(pc_branch)
    );

    initial begin
        // Initialize
        branch = 0; zero = 0; alu_result = 0; funct3 = 0;

        $display("Starting Branch Control Test...");
        $monitor("Time=%0t | BranchEn=%b | F3=%b | Zero=%b | ALU_LSB=%b | TAKEN=%b", 
                 $time, branch, funct3, zero, alu_result[0], pc_branch);

        #10;

        // Case 1: Branch signal is LOW 
        // Even if zero is 1, pc_branch should stay 0.
        branch = 0; funct3 = 3'b000; zero = 1; 
        #10;

        // Case 2: BEQ (funct3 = 000) 
        branch = 1; zero = 1; #10; // Should take branch
        zero = 0; #10;             // Should NOT take branch

        // Case 3: BNE (funct3 = 001) 
        funct3 = 3'b001; zero = 0; #10; // Should take branch
        zero = 1; #10;                  // Should NOT take branch

        // Case 4: BLT (funct3 = 100) 
        // Relies on ALU result[0] being 1 (True)
        funct3 = 3'b100; alu_result = 32'd1; #10; // Should take branch
        alu_result = 32'd0; #10;                  // Should NOT take branch

        // Case 5: BGE (funct3 = 101) 
        // Relies on ALU result[0] being 0 (meaning A is NOT less than B)
        funct3 = 3'b101; alu_result = 32'd0; #10; // Should take branch
        alu_result = 32'd1; #10;                  // Should NOT take branch

        // Case 6: BLTU (funct3 = 110) 
        funct3 = 3'b110; alu_result = 32'd1; #10; // Should take branch
        
        // Case 7: BGEU (funct3 = 111) 
        funct3 = 3'b111; alu_result = 32'd0; #10; // Should take branch

        $display("Branch Control Test Completed.");
        $finish;
    end

    initial begin
        $dumpfile("branch_control_op.vcd");
        $dumpvars(0, branch_control_tb);
    end

endmodule

/* 
Time=0 | BranchEn=0 | F3=000 | Zero=0 | ALU_LSB=0 | TAKEN=0
Time=10000 | BranchEn=0 | F3=000 | Zero=1 | ALU_LSB=0 | TAKEN=0
Time=20000 | BranchEn=1 | F3=000 | Zero=1 | ALU_LSB=0 | TAKEN=1
Time=30000 | BranchEn=1 | F3=000 | Zero=0 | ALU_LSB=0 | TAKEN=0
Time=40000 | BranchEn=1 | F3=001 | Zero=0 | ALU_LSB=0 | TAKEN=1
Time=50000 | BranchEn=1 | F3=001 | Zero=1 | ALU_LSB=0 | TAKEN=0
Time=60000 | BranchEn=1 | F3=100 | Zero=1 | ALU_LSB=1 | TAKEN=1
Time=70000 | BranchEn=1 | F3=100 | Zero=1 | ALU_LSB=0 | TAKEN=0
Time=80000 | BranchEn=1 | F3=101 | Zero=1 | ALU_LSB=0 | TAKEN=1
Time=90000 | BranchEn=1 | F3=101 | Zero=1 | ALU_LSB=1 | TAKEN=0
Time=100000 | BranchEn=1 | F3=110 | Zero=1 | ALU_LSB=1 | TAKEN=1
Time=110000 | BranchEn=1 | F3=111 | Zero=1 | ALU_LSB=0 | TAKEN=1
Branch Control Test Completed.
*/

VCDFiles/branch_control_op.vcd
$date
	Sat Apr 25 03:09:59 2026
$end
$version
	Icarus Verilog
$end
$timescale
	1ps
$end
$scope module branch_control_tb $end
$var wire 1 ! pc_branch $end
$var reg 32 " alu_result [31:0] $end
$var reg 1 # branch $end
$var reg 3 $ funct3 [2:0] $end
$var reg 1 % zero $end
$scope module uut $end
$var wire 32 & alu_result [31:0] $end
$var wire 1 # branch $end
$var wire 3 ' funct3 [2:0] $end
$var wire 1 % zero $end
$var reg 1 ! pc_branch $end
$upscope $end
$upscope $end
$enddefinitions $end
$comment Show the parameter values. $end
$dumpall
$end
#0
$dumpvars
b0 '
b0 &
0%
b0 $
0#
b0 "
0!
$end
#10000
1%
#20000
1!
1#
#30000
0!
0%
#40000
1!
b1 $
b1 '
#50000
0!
1%
#60000
1!
b1 "
b1 &
b100 $
b100 '
#70000
0!
b0 "
b0 &
#80000
1!
b101 $
b101 '
#90000
0!
b1 "
b1 &
#100000
1!
b110 $
b110 '
#110000
1!
b0 "
b0 &
b111 $
b111 '
