Source_Files/control_unit.v
// decodes the opcode to generate control signals for the datapath
module control_unit (
    input [6:0] opcode, // bits [6:0] of the instruction
    output reg reg_write, // 1=write to rd, 0=no write
    output reg alu_src, // 0=second operand from rs2, 1=second operand is immediate
    output reg mem_write, // 1=write to memory, 0=no write
    output reg mem_read, // 1=read from memory, 0=no read
    output reg mem_to_reg, // 1=write memory data to rd, 0=write ALU result to rd
    output reg branch, // 1=branch instruction, 0=no branch
    output reg jump, // 1=jump instruction (JAL), 0=no jump
    output reg jalr, // 1=jump instruction (JALR), 0=no jump
    output reg [1:0] alu_op
);

    always @(*) begin
        {reg_write, alu_src, mem_write, mem_read, mem_to_reg, branch, jump, jalr} = 8'b0;
        alu_op = 2'b00;

        case (opcode)
            7'b0110011: begin reg_write=1; alu_op=2'b10; end  // R-type (arithmetic and logic)
            7'b0010011: begin reg_write=1; alu_src=1; alu_op=2'b10; end // I-arith (immediate arithmetic and logic)
            7'b0000011: begin reg_write=1; alu_src=1; mem_read=1; mem_to_reg=1; end  // Load
            7'b0100011: begin alu_src=1; mem_write=1; end                            // Store
            7'b1100011: begin branch=1; alu_op=2'b01; end                            // Branch
            7'b0110111: begin reg_write=1; alu_src=1; alu_op=2'b11; end              // LUI (Load Upper Immediate)
            7'b0010111: begin reg_write=1; alu_src=1; alu_op=2'b10; end              // AUIPC (Add Upper Immediate to PC)
            7'b1101111: begin reg_write=1; jump=1; end                               // JAL (Jump and Link)
            7'b1100111: begin reg_write=1; alu_src=1; jalr=1; end                    // JALR (Jump and Link Register)
        endcase
    end

endmodule

TestBenches/tb_control_unit.v
`timescale 1ns / 1ps

module control_unit_tb();

    // Inputs
    reg [6:0] opcode;

    // Outputs
    wire reg_write;
    wire alu_src;
    wire mem_write;
    wire mem_read;
    wire mem_to_reg;
    wire branch;
    wire jump;
    wire jalr;
    wire [1:0] alu_op;

    // Instantiate the Unit Under Test (UUT)
    control_unit uut (
        .opcode(opcode), 
        .reg_write(reg_write), 
        .alu_src(alu_src), 
        .mem_write(mem_write), 
        .mem_read(mem_read), 
        .mem_to_reg(mem_to_reg), 
        .branch(branch), 
        .jump(jump), 
        .jalr(jalr), 
        .alu_op(alu_op)
    );

    initial begin
        $display("Starting Control Unit Test...");
        $display("Opcode  | RW | AS | MW | MR | M2R| BR | JP | JR | ALUOp");

        // R-type
        opcode = 7'b0110011; #10;
        check_signals("R-type");

        // I-arithmetic
        opcode = 7'b0010011; #10;
        check_signals("I-type");

        // Load 
        opcode = 7'b0000011; #10;
        check_signals("Load  ");

        // Store 
        opcode = 7'b0100011; #10;
        check_signals("Store ");

        // Branch 
        opcode = 7'b1100011; #10;
        check_signals("Branch");

        // LUI 
        opcode = 7'b0110111; #10;
        check_signals("LUI   ");

        // JAL 
        opcode = 7'b1101111; #10;
        check_signals("JAL   ");

        // JALR 
        opcode = 7'b1100111; #10;
        check_signals("JALR  ");

        $display("");
        $display("Control Unit Test Completed.");
        $finish;
    end

    // Task to print signals in a clean format
    task check_signals(input [47:0] label);
        begin
            $display("%b | %b  | %b  | %b  | %b  | %b  | %b  | %b  | %b  | %b   <- %s", 
                     opcode, reg_write, alu_src, mem_write, mem_read, 
                     mem_to_reg, branch, jump, jalr, alu_op, label);
        end
    endtask

    initial begin
        $dumpfile("control_unit_op.vcd");
        $dumpvars(0, control_unit_tb);
    end
      
endmodule

/* 
VCD OUTPUT:
Starting Control Unit Test...
Opcode  | RW | AS | MW | MR | M2R| BR | JP | JR | ALUOp
VCD info: dumpfile control_unit_op.vcd opened for output.
0110011 | 1  | 0  | 0  | 0  | 0  | 0  | 0  | 0  | 10   <- R-type
0010011 | 1  | 1  | 0  | 0  | 0  | 0  | 0  | 0  | 10   <- I-type
0000011 | 1  | 1  | 0  | 1  | 1  | 0  | 0  | 0  | 00   <- Load  
0100011 | 0  | 1  | 1  | 0  | 0  | 0  | 0  | 0  | 00   <- Store 
1100011 | 0  | 0  | 0  | 0  | 0  | 1  | 0  | 0  | 01   <- Branch
0110111 | 1  | 1  | 0  | 0  | 0  | 0  | 0  | 0  | 11   <- LUI   
1101111 | 1  | 0  | 0  | 0  | 0  | 0  | 1  | 0  | 00   <- JAL   
1100111 | 1  | 1  | 0  | 0  | 0  | 0  | 0  | 1  | 00   <- JALR 
*/

VCDFiles/control_unit_op.vcd
$date
	Sat Apr 25 03:16:32 2026
$end
$version
	Icarus Verilog
$end
$timescale
	1ps
$end
$scope module control_unit_tb $end
$var wire 1 ! reg_write $end
$var wire 1 " mem_write $end
$var wire 1 # mem_to_reg $end
$var wire 1 $ mem_read $end
$var wire 1 % jump $end
$var wire 1 & jalr $end
$var wire 1 ' branch $end
$var wire 1 ( alu_src $end
$var wire 2 ) alu_op [1:0] $end
$var reg 7 * opcode [6:0] $end
$scope module uut $end
$var wire 7 + opcode [6:0] $end
$var reg 2 , alu_op [1:0] $end
$var reg 1 ( alu_src $end
$var reg 1 ' branch $end
$var reg 1 & jalr $end
$var reg 1 % jump $end
$var reg 1 $ mem_read $end
$var reg 1 # mem_to_reg $end
$var reg 1 " mem_write $end
$var reg 1 ! reg_write $end
$upscope $end
$scope task check_signals $end
$var reg 48 - label [47:0] $end
$upscope $end
$upscope $end
$enddefinitions $end
$comment Show the parameter values. $end
$dumpall
$end
#0
$dumpvars
bx -
b10 ,
b110011 +
b110011 *
b10 )
0(
0'
0&
0%
0$
0#
0"
1!
$end
#10000
1(
b10 )
b10 ,
1!
b10011 *
b10011 +
b10100100010110101110100011110010111000001100101 -
#20000
1#
1$
b0 )
b0 ,
1!
1(
b11 *
b11 +
b10010010010110101110100011110010111000001100101 -
#30000
1"
0!
1(
0$
0#
b100011 *
b100011 +
b10011000110111101100001011001000010000000100000 -
#40000
b1 )
b1 ,
1'
0(
0"
b1100011 *
b1100011 +
b10100110111010001101111011100100110010100100000 -
#50000
1(
1!
b11 )
b11 ,
0'
b110111 *
b110111 +
b10000100111001001100001011011100110001101101000 -
#60000
1%
b0 )
b0 ,
1!
0(
b1101111 *
b1101111 +
b10011000101010101001001001000000010000000100000 -
#70000
1&
1(
1!
0%
b1100111 *
b1100111 +
b10010100100000101001100001000000010000000100000 -
#80000
b10010100100000101001100010100100010000000100000 -
