Source_Files/seg7_display.v
module seg7_display (
    input        clk,       // 100 MHz
    input        rst,
    input [15:0] data,
    output reg [6:0] seg,   // {A,B,C,D,E,F,G}
    output reg [3:0] an
);

    reg [17:0] cnt;
    always @(posedge clk or posedge rst)
        cnt <= rst ? 0 : cnt + 1;

    wire [1:0] sel = cnt[17:16];

    reg [3:0] nibble;
    always @(*) begin
        case (sel)
            2'b00: begin an = 4'b1110; nibble = data[3:0];   end
            2'b01: begin an = 4'b1101; nibble = data[7:4];   end
            2'b10: begin an = 4'b1011; nibble = data[11:8];  end
            2'b11: begin an = 4'b0111; nibble = data[15:12]; end
        endcase
    end

    always @(*) begin
        case (nibble)
            4'h0: seg = 7'b1000000; 
            4'h1: seg = 7'b1111001; 
            4'h2: seg = 7'b0100100; 
            4'h3: seg = 7'b0110000; 
            4'h4: seg = 7'b0011001; 
            4'h5: seg = 7'b0010010; 
            4'h6: seg = 7'b0000010; 
            4'h7: seg = 7'b1111000; 
            4'h8: seg = 7'b0000000; 
            4'h9: seg = 7'b0010000; 
            4'ha: seg = 7'b0001000; 
            4'hb: seg = 7'b0000011; 
            4'hc: seg = 7'b1000110; 
            4'hd: seg = 7'b0100001; 
            4'he: seg = 7'b0000110; 
            4'hf: seg = 7'b0001110; 
            default: seg = 7'b1111111; // Off
        endcase
    end

endmodule

Source_Files/data_mem.v
// Simple data memory module 

module data_mem #(parameter MEM_SIZE = 256) (
    input clk,
    input mem_write, mem_read,
    input [31:0] addr, write_data,
    output [31:0] read_data
);

    reg [31:0] mem [0:MEM_SIZE-1]; // 32-bit wide memory with MEM_SIZE entries
    integer i;
    // Initialize memory to zero
    initial for (i = 0; i < MEM_SIZE; i = i+1) mem[i] = 0; 

    // Write to memory on the rising edge of the clock if mem_write is asserted
    always @(posedge clk)
        if (mem_write) mem[addr[31:2]] <= write_data;

    // Read from memory combinationally if mem_read is asserted
    assign read_data = mem_read ? mem[addr[31:2]] : 0;

endmodule

Source_Files/branch_control.v
// decides if a branch should be taken based on the branch type and ALU results
// brach means to jump to a different instruction address if a certain condition is met 
module branch_control (
    input branch,
    input zero,
    input [31:0] alu_result,
    input [2:0] funct3,
    output reg pc_branch
);

    always @(*) begin
        pc_branch = 1'b0;
        if (branch) begin
            case (funct3)
                3'b000: pc_branch = zero; // BEQ (branch if equal)
                3'b001: pc_branch = ~zero; // BNE (branch if not equal)
                3'b100: pc_branch = alu_result[0]; // BLT  (branch if less than, signed)
                3'b101: pc_branch = ~alu_result[0]; // BGE  (branch if greater than or equal, signed)
                3'b110: pc_branch = alu_result[0]; // BLTU (branch if less than, unsigned)
                3'b111: pc_branch = ~alu_result[0]; // BGEU (branch if greater than or equal, unsigned)
                default: pc_branch = 1'b0;
            endcase
        end
    end

endmodule

Source_Files/alu.v
module alu (
    input [31:0] a, b,
    input [3:0] alu_ctrl,
    output reg [31:0] result,
    output zero
);

    always @(*) begin
        case (alu_ctrl)
            4'b0000: result = a & b; // And
            4'b0001: result = a | b; // OR
            4'b0010: result = a + b; // ADD
            4'b0110: result = a - b; // SUB
            4'b0111: result = ($signed(a) < $signed(b)) ? 1 : 0; // SLT (signed comparison)
            4'b1000: result = a ^ b; // XOR
            4'b1001: result = a >> b[4:0]; // SRL (shift right logical)
            4'b1010: result = $signed(a) >>> b[4:0]; // SRA (shift right arithmetic)
            4'b1011: result = a << b[4:0]; // SLL (shift left logical)
            4'b1100: result = (a < b) ? 1 : 0; // SLTU (set less than unsigned)
            4'b1101: result = b; // LUI: pass B (upper immediate)
            default: result = 0; // Default case to handle undefined control signals
        endcase
    end

    assign zero = (result == 0); // Zero flag is set if the result is zero

endmodule

Source_Files/alu_control.v
module alu_control (
    input [1:0] alu_op, // defines the type of instruction 
    input [2:0] funct3, // defines the specific operation for R-type and I-type instructions
    input [6:0] funct7, // differentiates between certain R-type instructions (ADD vs SUB)
    output reg [3:0] alu_ctrl // final control signal for the ALU 
);

    always @(*) begin
        case (alu_op)
            2'b00: alu_ctrl = 4'b0010; // Load/Store: ADD
            2'b01: alu_ctrl = 4'b0110; // Branch: SUB (for BEQ/BNE), BLT/BGE handled in branch_control
            2'b11: alu_ctrl = 4'b1101; // LUI: pass B
            2'b10: case (funct3) // R-type / I-type
                3'b000: alu_ctrl = (funct7[5]) ? 4'b0110 : 4'b0010; // SUB/ADD
                3'b001: alu_ctrl = 4'b1011; // SLL
                3'b010: alu_ctrl = 4'b0111; // SLT
                3'b011: alu_ctrl = 4'b1100; // SLTU
                3'b100: alu_ctrl = 4'b1000; // XOR
                3'b101: alu_ctrl = (funct7[5]) ? 4'b1010 : 4'b1001; // SRA/SRL
                3'b110: alu_ctrl = 4'b0001; // OR
                3'b111: alu_ctrl = 4'b0000; // AND
                default: alu_ctrl = 4'b0010; // Default to ADD for unknown funct3
            endcase
            default: alu_ctrl = 4'b0010; // Default to ADD for unknown alu_op
        endcase
    end

endmodule

Source_Files/imm_gen.v
// Immediate Generator
module imm_gen (
    input [31:0] instr,
    output reg [31:0] imm_ext
);
    // Generate the immediate value based on the instruction type
    // TYPES:
    // I-type: arithmetic, load, jalr
    // S-type: store
    // B-type: branch
    // U-type: lui, auipc
    // J-type: jal
    always @(*) begin
        case (instr[6:0])
            7'b0010011, // I-type and jalr 
            7'b0000011, // I-type load
            7'b1100111: imm_ext = {{20{instr[31]}}, instr[31:20]}; // I-type
            7'b0100011: imm_ext = {{20{instr[31]}}, instr[31:25], instr[11:7]}; // S-type
            7'b1100011: imm_ext = {{19{instr[31]}}, instr[31], instr[7], instr[30:25], instr[11:8], 1'b0}; // B-type
            7'b0110111, // U-type and lui
            7'b0010111: imm_ext = {instr[31:12], 12'b0}; // U-type
            7'b1101111: imm_ext = {{11{instr[31]}}, instr[31], instr[19:12], instr[20], instr[30:21], 1'b0}; // J-type
            default:    imm_ext = 0;
        endcase
    end

endmodule

Source_Files/register_file.v
// Register file with 32 registers, each 32 bits wide.
module register_file (
    input clk,
    input reg_write, // control signal that enables writing to the register file
    input [4:0] rs1, rs2, rd, // rs1 and rs2 are source register indices, rd is the destination register index
    input [31:0] write_data,
    output [31:0] read_data1, read_data2
);

    reg [31:0] registers [0:31]; 
    integer i;
    // Initialize all registers to 0 at the start of the simulation.
    initial for (i = 0; i < 32; i = i+1) registers[i] = 0; 

    // Write to the register file on the rising edge of the clock if reg_write is given
    always @(posedge clk)
        if (reg_write && rd != 0) registers[rd] <= write_data;

    // Read data from the register file. If rs1 or rs2 is 0, return 0 
    assign read_data1 = (rs1 == 0) ? 0 : registers[rs1];
    assign read_data2 = (rs2 == 0) ? 0 : registers[rs2];

endmodule

Source_Files/control_unit.v
// decodes the opcode to generate control signals for the datapath
module control_unit (
    input [6:0] opcode, // bits [6:0] of the instruction
    output reg reg_write, // 1=write to rd, 0=no write
    output reg alu_src, // 0=second operand from rs2, 1=second operand is immediate
    output reg mem_write, // 1=write to memory, 0=no write
    output reg mem_read, // 1=read from memory, 0=no read
    output reg mem_to_reg, // 1=write memory data to rd, 0=write ALU result to rd
    output reg branch, // 1=branch instruction, 0=no branch
    output reg jump, // 1=jump instruction (JAL), 0=no jump
    output reg jalr, // 1=jump instruction (JALR), 0=no jump
    output reg [1:0] alu_op
);

    always @(*) begin
        {reg_write, alu_src, mem_write, mem_read, mem_to_reg, branch, jump, jalr} = 8'b0;
        alu_op = 2'b00;

        case (opcode)
            7'b0110011: begin reg_write=1; alu_op=2'b10; end  // R-type (arithmetic and logic)
            7'b0010011: begin reg_write=1; alu_src=1; alu_op=2'b10; end // I-arith (immediate arithmetic and logic)
            7'b0000011: begin reg_write=1; alu_src=1; mem_read=1; mem_to_reg=1; end  // Load
            7'b0100011: begin alu_src=1; mem_write=1; end                            // Store
            7'b1100011: begin branch=1; alu_op=2'b01; end                            // Branch
            7'b0110111: begin reg_write=1; alu_src=1; alu_op=2'b11; end              // LUI (Load Upper Immediate)
            7'b0010111: begin reg_write=1; alu_src=1; alu_op=2'b10; end              // AUIPC (Add Upper Immediate to PC)
            7'b1101111: begin reg_write=1; jump=1; end                               // JAL (Jump and Link)
            7'b1100111: begin reg_write=1; alu_src=1; jalr=1; end                    // JALR (Jump and Link Register)
        endcase
    end

endmodule

Source_Files/instr_mem.v
// Instruction memory 
// decodes the instruction address and outputs the instruction at that address from a hex file
// hex file format: each line contains a 32-bit instruction in hexadecimal, without the "0x" prefix
module instr_mem #(parameter MEM_SIZE = 256) (
    input  [31:0] addr,
    output [31:0] instr
);

    reg [31:0] mem [0:MEM_SIZE-1];
    integer i;

    initial begin
        for (i = 0; i < MEM_SIZE; i = i+1)
            mem[i] = 32'h00000013; // NOP
        $readmemh("program.hex", mem);
    end
    // The instruction address is word-aligned, so we use bits [31:2] to index the memory
    // word-aligned means that the address is a multiple of 4, so the last two bits are always 0 and can be ignored
    assign instr = mem[addr[31:2]];

endmodule

Source_Files/riscv_top.v
// RISC: Reduced Instruction Set Computer
// RV32I: RISC-V 32-bit Integer instructions
// Single-Cycle: Each instruction completes in one clock cycle

module riscv_top (
    input clk,
    input rst,
    output [6:0] seg,
    output [3:0] an
);

    // Program Counter 
    // On every clock cycle, decides if to jump/branch or go to next instruction
    reg  [31:0] pc;
    wire [31:0] pc_plus4 = pc + 4; // input to PC for normal sequential execution
    wire [31:0] pc_next; // Next instruction address

    always @(posedge clk or posedge rst)
        pc <= rst ? 0 : pc_next;

    // Instruction fetch
    // Act as the ROM (Read Only Memory) for instructions
    // take a 32-bit address (pc) and output the 32-bit instruction at that address
    wire [31:0] instr;
    instr_mem imem (.addr(pc), .instr(instr));

    // Decode fields
    wire [6:0] opcode = instr[6:0]; // Opcode determines the instruction type and operation
    wire [4:0] rd = instr[11:7]; // Destination register address (for R-type and I-type)
    wire [2:0] funct3 = instr[14:12]; // Function code for ALU operations and branch types
    wire [4:0] rs1 = instr[19:15]; // Source register 1 address
    wire [4:0] rs2 = instr[24:20]; // Source register 2 address (for R-type)
    wire [6:0] funct7 = instr[31:25]; // Additional function code for R-type instructions (distinguishes ADD vs SUB)

    // Control signals
    // The control unit takes the opcode and generates signals that control the data path:
    // reg_write: whether to write back to the register file
    // alu_src: whether the second ALU operand is from the register file or immediate
    // mem_write: whether to write to data memory
    // mem_read: whether to read from data memory
    // mem_to_reg: whether to write back ALU result or memory data to register file
    // branch: whether the instruction is a branch (BEQ, BNE, BLT, BGE)
    // jump: whether the instruction is a jump (JAL)
    // jalr: whether the instruction is JALR (jump and link register)
    wire reg_write, alu_src, mem_write, mem_read, mem_to_reg, branch, jump, jalr;
    
    // alu_op: specifies the ALU operation type
    wire [1:0] alu_op; 

    control_unit ctrl (
        .opcode(opcode),.reg_write(reg_write), .alu_src(alu_src),
        .mem_write(mem_write), .mem_read(mem_read), .mem_to_reg(mem_to_reg),
        .branch(branch), .jump(jump), .jalr(jalr), .alu_op(alu_op)
    );

    // Register file
    // handles the storage and retrieval of register values
    // rs1, rs2 for reading; rd for writing
    wire [31:0] read_data1, read_data2, write_data;
    register_file regfile (
        .clk(clk), .reg_write(reg_write),
        .rs1(rs1), .rs2(rs2), .rd(rd),
        .write_data(write_data),
        .read_data1(read_data1), .read_data2(read_data2)
    );

    // Immediate generator
    // takes the instruction and extracts the immediate value 
    // based on the instruction type (I-type, S-type, B-type, U-type, J-type)
    wire [31:0] imm_ext;
    imm_gen igen (.instr(instr), .imm_ext(imm_ext));

    // ALU (Arithmetic Logic Unit)
    // Performs arithmetic and logical operations based on the control signals
    // alu_control unit decodes the ALU operation from alu_op, funct3, and funct7
    // alu takes two operands (from register file or immediate) and produces a result and zero flag
    wire [3:0] alu_ctrl;
    alu_control alu_ctrl_unit (.alu_op(alu_op), .funct3(funct3), .funct7(funct7), .alu_ctrl(alu_ctrl));

    // AUIPC (Add Upper Immediate to PC)
    // auipc is used to convert a 12 bit immediate into a 32-bit address by adding it to the current PC
    // for operand A, use PC for AUIPC, otherwise use read_data1 from register file
    // for operand B, use either the immediate (for I-type) or the second register value (for R-type)
    wire [31:0] alu_a = (opcode == 7'b0010111) ? pc : read_data1; 
    wire [31:0] alu_b = alu_src ? imm_ext : read_data2;
    wire [31:0] alu_result;
    wire zero; // Zero flag for branch decisions
    alu main_alu (.a(alu_a), .b(alu_b), .alu_ctrl(alu_ctrl), .result(alu_result), .zero(zero));

    // Branch decision
    // take the branch control signals and ALU results to determine if a branch should be taken
    // if branch is taken, pc_next will be the branch target
    // otherwise, it will be pc_plus4
    wire pc_branch;
    branch_control bctrl (
        .branch(branch), .zero(zero),
        .alu_result(alu_result), .funct3(funct3), .pc_branch(pc_branch)
    );

    // PC next
    // For jumps and branches, calculate the target address
    // otherwise, go to the next sequential instruction (pc + 4)
    wire [31:0] branch_target = pc + imm_ext;
    wire [31:0] jalr_target   = (read_data1 + imm_ext) & ~32'h1;

    // jalr: target address is computed by adding the immediate to the value in rs1, and then clearing the least significant bit 
    // jump (JAL): target address is computed by adding the immediate to the current PC
    // branch: target address is computed by adding the immediate to the current PC, but only taken if the branch condition is met 
    assign pc_next = jalr ? jalr_target :
                     jump ? branch_target :
                     pc_branch ? branch_target : pc_plus4;

    // Data memory
    // Acts as the RAM for load/store instructions
    // Takes an address and either reads data from that address or writes data to that address based on the control signals
    wire [31:0] mem_read_data;
    data_mem dmem (
        .clk(clk), .mem_write(mem_write), .mem_read(mem_read),
        .addr(alu_result), .write_data(read_data2), .read_data(mem_read_data)
    );

    // Write-back
    // Determines what data to write back to the register file based on the instruction type
    assign write_data = (jump || jalr) ? pc_plus4     : // For JAL and JALR, write the return address (PC + 4) to rd
                        mem_to_reg ? mem_read_data : alu_result; // For load instructions, write memory data; otherwise, write ALU result

    // Display x10 (a0) lower 16 bits on 7-segment
    seg7_display disp (
        .clk(clk), .rst(rst),
        .data(regfile.registers[10][15:0]), 
        .seg(seg), .an(an)
    );

endmodule

TestBenches/tb_riscv.v
`timescale 1ns / 1ps

module riscv_top_tb();

    // Inputs
    reg clk;
    reg rst;

    // Outputs
    wire [6:0] seg;
    wire [3:0] an;

    // Instantiate the Top Level RISC-V Processor
    riscv_top uut (
        .clk(clk), 
        .rst(rst), 
        .seg(seg), 
        .an(an)
    );

    // Clock generation (10ns period = 100MHz)
    always #5 clk = ~clk;

    initial begin
        // Initialize Signals
        clk = 0;
        rst = 1; // Start in reset

        $display("System Reset Asserted...");
        #20;
        rst = 0; // Release reset
        $display("System Reset Released. Starting Execution...");

        // Monitor PC and core internal signals for debugging
        $display("Time | PC       | Instr    | x10 (a0) Value");

        repeat (10) begin
            @(posedge clk);
            #1; // Small delay to allow signals to settle after clock edge
            $display("%4t | %h | %h | %d", 
                     $time, uut.pc, uut.instr, uut.regfile.registers[10]);
        end

        $display("Simulation timeout reached.");
        $finish;
    end

    initial begin
        $dumpfile("riscv_top_op.vcd");
        $dumpvars(0, riscv_top_tb);
    end
      
endmodule

/*
VCD info: dumpfile riscv_top_op.vcd opened for output.
System Reset Released. Starting Execution...
Time | PC       | Instr    | x10 (a0) Value
26000 | 00000004 | 00a00113 |          0
36000 | 00000008 | 00208533 |          0
46000 | 0000000c | 40208533 |         40
56000 | 00000010 | 0020f533 |         20
66000 | 00000014 | 0020e533 |         10
76000 | 00000018 | 0020c533 |         30
86000 | 0000001c | 0020a533 |         20
96000 | 00000020 | 00a52023 |          0
106000 | 00000024 | 00052503 |          0
116000 | 00000028 | 00a50463 |          0
Simulation timeout reached.
*/

VCDFiles/riscv_top_op.vcd
$date
	Sat Apr 25 03:43:27 2026
$end
$version
	Icarus Verilog
$end
$timescale
	1ps
$end
$scope module riscv_top_tb $end
$var wire 7 ! seg [6:0] $end
$var wire 4 " an [3:0] $end
$var reg 1 # clk $end
$var reg 1 $ rst $end
$scope module uut $end
$var wire 1 # clk $end
$var wire 32 % jalr_target [31:0] $end
$var wire 1 $ rst $end
$var wire 1 & zero $end
$var wire 32 ' write_data [31:0] $end
$var wire 7 ( seg [6:0] $end
$var wire 5 ) rs2 [4:0] $end
$var wire 5 * rs1 [4:0] $end
$var wire 1 + reg_write $end
$var wire 32 , read_data2 [31:0] $end
$var wire 32 - read_data1 [31:0] $end
$var wire 5 . rd [4:0] $end
$var wire 32 / pc_plus4 [31:0] $end
$var wire 32 0 pc_next [31:0] $end
$var wire 1 1 pc_branch $end
$var wire 7 2 opcode [6:0] $end
$var wire 1 3 mem_write $end
$var wire 1 4 mem_to_reg $end
$var wire 32 5 mem_read_data [31:0] $end
$var wire 1 6 mem_read $end
$var wire 1 7 jump $end
$var wire 1 8 jalr $end
$var wire 32 9 instr [31:0] $end
$var wire 32 : imm_ext [31:0] $end
$var wire 7 ; funct7 [6:0] $end
$var wire 3 < funct3 [2:0] $end
$var wire 32 = branch_target [31:0] $end
$var wire 1 > branch $end
$var wire 4 ? an [3:0] $end
$var wire 1 @ alu_src $end
$var wire 32 A alu_result [31:0] $end
$var wire 2 B alu_op [1:0] $end
$var wire 4 C alu_ctrl [3:0] $end
$var wire 32 D alu_b [31:0] $end
$var wire 32 E alu_a [31:0] $end
$var reg 32 F pc [31:0] $end
$scope module alu_ctrl_unit $end
$var wire 3 G funct3 [2:0] $end
$var wire 7 H funct7 [6:0] $end
$var wire 2 I alu_op [1:0] $end
$var reg 4 J alu_ctrl [3:0] $end
$upscope $end
$scope module bctrl $end
$var wire 3 K funct3 [2:0] $end
$var wire 1 & zero $end
$var wire 1 > branch $end
$var wire 32 L alu_result [31:0] $end
$var reg 1 1 pc_branch $end
$upscope $end
$scope module ctrl $end
$var wire 7 M opcode [6:0] $end
$var reg 2 N alu_op [1:0] $end
$var reg 1 @ alu_src $end
$var reg 1 > branch $end
$var reg 1 8 jalr $end
$var reg 1 7 jump $end
$var reg 1 6 mem_read $end
$var reg 1 4 mem_to_reg $end
$var reg 1 3 mem_write $end
$var reg 1 + reg_write $end
$upscope $end
$scope module disp $end
$var wire 1 # clk $end
$var wire 16 O data [15:0] $end
$var wire 1 $ rst $end
$var wire 2 P sel [1:0] $end
$var reg 4 Q an [3:0] $end
$var reg 18 R cnt [17:0] $end
$var reg 4 S nibble [3:0] $end
$var reg 7 T seg [6:0] $end
$upscope $end
$scope module dmem $end
$var wire 1 # clk $end
$var wire 1 6 mem_read $end
$var wire 1 3 mem_write $end
$var wire 32 U write_data [31:0] $end
$var wire 32 V read_data [31:0] $end
$var wire 32 W addr [31:0] $end
$var parameter 32 X MEM_SIZE $end
$var integer 32 Y i [31:0] $end
$upscope $end
$scope module igen $end
$var wire 32 Z instr [31:0] $end
$var reg 32 [ imm_ext [31:0] $end
$upscope $end
$scope module imem $end
$var wire 32 \ addr [31:0] $end
$var wire 32 ] instr [31:0] $end
$var parameter 32 ^ MEM_SIZE $end
$var integer 32 _ i [31:0] $end
$upscope $end
$scope module main_alu $end
$var wire 32 ` a [31:0] $end
$var wire 4 a alu_ctrl [3:0] $end
$var wire 32 b b [31:0] $end
$var wire 1 & zero $end
$var reg 32 c result [31:0] $end
$upscope $end
$scope module regfile $end
$var wire 1 # clk $end
$var wire 5 d rd [4:0] $end
$var wire 1 + reg_write $end
$var wire 5 e rs1 [4:0] $end
$var wire 5 f rs2 [4:0] $end
$var wire 32 g write_data [31:0] $end
$var wire 32 h read_data2 [31:0] $end
$var wire 32 i read_data1 [31:0] $end
$var integer 32 j i [31:0] $end
$upscope $end
$upscope $end
$upscope $end
$enddefinitions $end
$comment Show the parameter values. $end
$dumpall
b100000000 ^
b100000000 X
$end
#0
$dumpvars
b100000 j
b0 i
b0 h
b11110 g
b11110 f
b0 e
b1 d
b11110 c
b11110 b
b10 a
b0 `
b100000000 _
b1111000000000000010010011 ]
b0 \
b11110 [
b1111000000000000010010011 Z
b100000000 Y
b11110 W
b0 V
b0 U
b1000000 T
b0 S
b0 R
b1110 Q
b0 P
b0 O
b10 N
b10011 M
b11110 L
b0 K
b10 J
b10 I
b0 H
b0 G
b0 F
b0 E
b11110 D
b10 C
b10 B
b11110 A
1@
b1110 ?
0>
b11110 =
b0 <
b0 ;
b11110 :
b1111000000000000010010011 9
08
07
06
b0 5
04
03
b10011 2
01
b100 0
b100 /
b1 .
b0 -
b0 ,
1+
b0 *
b11110 )
b1000000 (
b11110 '
0&
b11110 %
1$
0#
b1110 "
b1000000 !
$end
#5000
1#
#10000
0#
#15000
1#
#20000
0#
0$
#25000
b1010 '
b1010 g
b1010 A
b1010 L
b1010 W
b1010 c
b1000 0
b1010 %
b1010 D
b1010 b
b1010 )
b1010 f
b10 .
b10 d
b1010 :
b1010 [
b101000000000000100010011 9
b101000000000000100010011 Z
b101000000000000100010011 ]
b1000 /
b1110 =
b100 F
b100 \
b1 R
1#
#30000
0#
#35000
b101000 '
b101000 g
b11110 E
b11110 `
0&
b101000 A
b101000 L
b101000 W
b101000 c
b1100 0
b1010 ,
b1010 U
b1010 h
b11110 -
b11110 i
b10 B
b10 I
b10 N
1+
0@
b11110 %
b1010 D
b1010 b
b10 )
b10 f
b1 *
b1 e
b1010 .
b1010 d
b110011 2
b110011 M
b0 :
b0 [
b1000001000010100110011 9
b1000001000010100110011 Z
b1000001000010100110011 ]
b10 R
b1100 /
b1000 =
b1000 F
b1000 \
1#
#40000
0#
#45000
b10100 '
b10100 g
b10100 A
b10100 L
b10100 W
b10100 c
b10000 0
b110 C
b110 J
b110 a
b0 !
b0 (
b0 T
b100000 ;
b100000 H
b1000 S
b1000000001000001000010100110011 9
b1000000001000001000010100110011 Z
b1000000001000001000010100110011 ]
b101000 O
b10000 /
b1100 =
b1100 F
b1100 \
b11 R
1#
#50000
0#
#55000
b1010 '
b1010 g
b1010 A
b1010 L
b1010 W
b1010 c
b10100 0
b0 C
b0 J
b0 a
b11001 !
b11001 (
b11001 T
b0 ;
b0 H
b111 <
b111 G
b111 K
b100 S
b1000001111010100110011 9
b1000001111010100110011 Z
b1000001111010100110011 ]
b10100 O
b100 R
b10100 /
b10000 =
b10000 F
b10000 \
1#
#60000
0#
#65000
b11110 '
b11110 g
b11110 A
b11110 L
b11110 W
b11110 c
b11000 0
b1 C
b1 J
b1 a
b1000 !
b1000 (
b1000 T
b110 <
b110 G
b110 K
b1010 S
b1000001110010100110011 9
b1000001110010100110011 Z
b1000001110010100110011 ]
b1010 O
b11000 /
b10100 =
b10100 F
b10100 \
b101 R
1#
#70000
0#
#75000
b10100 '
b10100 g
b10100 A
b10100 L
b10100 W
b10100 c
b11100 0
b1000 C
b1000 J
b1000 a
b110 !
b110 (
b110 T
b100 <
b100 G
b100 K
b1110 S
b1000001100010100110011 9
b1000001100010100110011 Z
b1000001100010100110011 ]
b11110 O
b110 R
b11100 /
b11000 =
b11000 F
b11000 \
1#
#80000
0#
#85000
b0 '
b0 g
1&
b0 A
b0 L
b0 W
b0 c
b100000 0
b111 C
b111 J
b111 a
b11001 !
b11001 (
b11001 T
b10 <
b10 G
b10 K
b100 S
b1000001010010100110011 9
b1000001010010100110011 Z
b1000001010010100110011 ]
b10100 O
b100000 /
b11100 =
b11100 F
b11100 \
b111 R
1#
#90000
0#
#95000
b0 %
b0 E
b0 `
b0 D
b0 b
b10 C
b10 J
b10 a
b100100 0
b0 ,
b0 U
b0 h
b0 -
b0 i
13
1@
b0 B
b0 I
b0 N
0+
b1000000 !
b1000000 (
b1000000 T
b1010 )
b1010 f
b1010 *
b1010 e
b0 .
b0 d
b100011 2
b100011 M
b0 S
b101001010010000000100011 9
b101001010010000000100011 Z
b101001010010000000100011 ]
b0 O
b1000 R
b100100 /
b100000 =
b100000 F
b100000 \
1#
#100000
0#
#105000
b101000 0
14
16
1+
1@
03
b0 )
b0 f
b1010 .
b1010 d
b11 2
b11 M
b1010010010100000011 9
b1010010010100000011 Z
b1010010010100000011 ]
b101000 /
b100100 =
b100100 F
b100100 \
b1001 R
1#
#110000
0#
#115000
b0 '
b0 g
1&
b0 A
b0 L
b0 W
b0 c
b110000 0
b110 C
b110 J
b110 a
11
b1 B
b1 I
b1 N
1>
0+
0@
06
04
b1000 %
b0 D
b0 b
b1010 )
b1010 f
b0 <
b0 G
b0 K
b1000 .
b1000 d
b1100011 2
b1100011 M
b1000 :
b1000 [
b101001010000010001100011 9
b101001010000010001100011 Z
b101001010000010001100011 ]
b1010 R
b101100 /
b110000 =
b101000 F
b101000 \
1#
